pilpxi/__init__.py
pilpxi-1.74.dist-info/licenses/LICENSE.txt
pilpxi-1.74.dist-info/METADATA
pilpxi-1.74.dist-info/WHEEL
pilpxi-1.74.dist-info/top_level.txt
pilpxi-1.74.dist-info/RECORD
