Metadata-Version: 2.4
Name: Pilpxi
Version: 1.74
Summary: Python wrapper library for Pickering PXI Direct-IO driver
Home-page: https://downloads.pickeringtest.info/downloads/drivers/PXI_Drivers/
Author: Pickering Interfaces
Author-email: Pickering Interfaces <support@pickeringtest.com>
License: Copyright (c) 2017-2026 Pickering Interfaces Ltd.
Project-URL: homepage, https://downloads.pickeringtest.info/downloads/drivers/PXI_Drivers/
License-File: LICENSE.txt
Requires-Dist: enum34
Dynamic: author
Dynamic: home-page
Dynamic: license-file
